[{"id":"architecture","name":{"zh":"架构与后端","en":"Architecture & Backend"},"description":{"zh":"系统设计、服务边界、高并发 API 与遗留系统演进。","en":"System design, service boundaries, high-throughput APIs, and pragmatic legacy evolution."},"level":"signature","skills":[{"name":"PHP / Laravel","years":15,"level":"Expert"},{"name":"System design","years":12,"level":"Expert"},{"name":"MySQL / Redis","years":12,"level":"Expert"},{"name":"API & integrations","years":12,"level":"Expert"}]},{"id":"delivery","name":{"zh":"云与交付","en":"Cloud & Delivery"},"description":{"zh":"将可靠交付、可观测性与清晰的基础设施实践融入日常研发。","en":"Reliable delivery, observability, and infrastructure that stays understandable."},"level":"core","skills":[{"name":"Docker / CI/CD","years":9,"level":"Expert"},{"name":"Cloudflare","years":5,"level":"Advanced"},{"name":"Kubernetes","years":4,"level":"Advanced"},{"name":"Application security","years":8,"level":"Advanced"}]},{"id":"product","name":{"zh":"产品与体验","en":"Product & Experience"},"description":{"zh":"以业务目标为起点，协同团队交付可衡量、可持续的产品结果。","en":"Turning business goals into measurable, sustainable product outcomes with teams."},"level":"strong","skills":[{"name":"Vue / TypeScript","years":7,"level":"Advanced"},{"name":"E-commerce","years":10,"level":"Expert"},{"name":"Team leadership","years":10,"level":"Expert"},{"name":"AI workflows","years":2,"level":"Working knowledge"}]},{"id":"Products","name":{"zh":"产品","en":"Products"},"description":{"zh":"Enthusiastically promote fully tested niches before resource maximizing alignments. Continually.","en":"Enthusiastically promote fully tested niches before resource maximizing alignments. Continually."},"level":"core","skills":[{"name":"PIM","years":1,"level":"Advanced"},{"name":"CMS","years":1,"level":"Advanced"},{"name":"Shopping Cart","years":1,"level":"Advanced"}]}]
